sphinx_removed_in/__init__.py
sphinx_removed_in-0.2.3.dist-info/LICENSE
sphinx_removed_in-0.2.3.dist-info/METADATA
sphinx_removed_in-0.2.3.dist-info/WHEEL
sphinx_removed_in-0.2.3.dist-info/top_level.txt
sphinx_removed_in-0.2.3.dist-info/RECORD
