Metadata-Version: 2.1
Name: sphinx-removed-in
Version: 0.2.3
Summary: versionremoved and removed-in directives for Sphinx
Home-page: https://github.com/MrSenko/sphinx-removed-in
Author: Alexander Todorov
Author-email: atodorov@MrSenko.com
License: BSD
Keywords: Sphinx
Classifier: Development Status :: 5 - Production/Stable
Classifier: Environment :: Console
Classifier: Environment :: Web Environment
Classifier: Framework :: Sphinx
Classifier: Framework :: Sphinx :: Extension
Classifier: Intended Audience :: Developers
Classifier: Intended Audience :: Education
Classifier: License :: OSI Approved :: BSD License
Classifier: Operating System :: OS Independent
Classifier: Programming Language :: Python
Classifier: Programming Language :: Python :: 2
Classifier: Programming Language :: Python :: 3
Classifier: Topic :: Documentation
Classifier: Topic :: Documentation :: Sphinx
Classifier: Topic :: Text Processing
Classifier: Topic :: Utilities
License-File: LICENSE
Requires-Dist: Sphinx
